{"ongoing_trials": {}, "hyperparameters": {"space": [{"class_name": "Choice", "config": {"name": "learning_rate", "default": 0.001, "conditions": [], "values": [0.001, 0.0007, 0.0003], "ordered": true}}], "values": {"learning_rate": 0.001}}, "start_order": ["00", "01", "02"], "end_order": ["00", "01", "02"], "run_times": {"00": 1, "01": 1, "02": 1}, "retry_queue": [], "seed": 1978, "seed_state": 1985, "tried_so_far": ["4ee1649c40a9b5875cc07dc8a0530b07", "3e65da5b8ef22e0d345875ebff197b31", "6b31eabc680de57aa215b3bd268fed60"], "id_to_hash": {"00": "6b31eabc680de57aa215b3bd268fed60", "01": "4ee1649c40a9b5875cc07dc8a0530b07", "02": "3e65da5b8ef22e0d345875ebff197b31"}, "display": {"search_start": "2025-06-20T20:11:21.916804", "trial_start": {"00": "2025-06-20T20:11:21.916804", "01": "2025-06-20T20:12:34.128656", "02": "2025-06-20T20:14:00.099885"}, "trial_number": {"00": 1, "01": 2, "02": 3}}}